reminder_sink/__init__.py
reminder_sink/__main__.py
reminder_sink/py.typed
reminder_sink-0.1.2.dist-info/licenses/LICENSE
reminder_sink-0.1.2.dist-info/METADATA
reminder_sink-0.1.2.dist-info/WHEEL
reminder_sink-0.1.2.dist-info/entry_points.txt
reminder_sink-0.1.2.dist-info/top_level.txt
reminder_sink-0.1.2.dist-info/RECORD
