Metadata-Version: 2.4
Name: reminder_sink
Version: 0.1.2
Summary: A unobtrusive, scriptable reminder/habit/todo task-runner
Author: purarue
License-Expression: MIT
Project-URL: Homepage, https://github.com/purarue/reminder-sink
Classifier: Programming Language :: Python
Classifier: Programming Language :: Python :: 3
Classifier: Programming Language :: Python :: 3 :: Only
Classifier: Programming Language :: Python :: 3.10
Classifier: Programming Language :: Python :: 3.11
Classifier: Programming Language :: Python :: 3.12
Classifier: Programming Language :: Python :: 3.13
Requires-Python: >=3.10
License-File: LICENSE
Requires-Dist: click>=8.1.6
Requires-Dist: typing-extensions; python_version < "3.10"
Provides-Extra: testing
Requires-Dist: flake8; extra == "testing"
Requires-Dist: mypy; extra == "testing"
Dynamic: license-file
